plhtools/__init__.py
plhtools/configuration.py
plhtools/encryption_and_decryption.py
plhtools/es.py
plhtools/mysql.py
plhtools/redis.py
plhtools-1.1.31.dist-info/LICENSE.txt
plhtools-1.1.31.dist-info/METADATA
plhtools-1.1.31.dist-info/WHEEL
plhtools-1.1.31.dist-info/top_level.txt
plhtools-1.1.31.dist-info/RECORD
