Metadata-Version: 2.1
Name: plhtools
Version: 1.1.31
Summary: 彭麟汉的工具包
Home-page: https://mp.weixin.qq.com/s/9FQ-Tun5FbpBepBAsdY62w
Author: penglinhan
Author-email: 2453995079@qq.com
License: MIT License
Platform: all
Classifier: Intended Audience :: Developers
Classifier: Operating System :: OS Independent
Classifier: Natural Language :: Chinese (Simplified)
Classifier: Programming Language :: Python
Classifier: Programming Language :: Python :: 2
Classifier: Programming Language :: Python :: 2.7
Classifier: Programming Language :: Python :: 3
Classifier: Programming Language :: Python :: 3.5
Classifier: Programming Language :: Python :: 3.6
Classifier: Programming Language :: Python :: 3.7
Classifier: Programming Language :: Python :: 3.8
Classifier: Programming Language :: Python :: 3.9
Classifier: Topic :: Software Development :: Libraries
License-File: LICENSE.txt
Requires-Dist: pycryptodome
Requires-Dist: eciespy
Requires-Dist: configparser
Requires-Dist: pymysql
Requires-Dist: pandas
Requires-Dist: sqlalchemy
Requires-Dist: PyExecJS
Requires-Dist: ltp
Requires-Dist: elasticsearch-dsl
Requires-Dist: openpyxl (==3.0.10)
Requires-Dist: bs4
Requires-Dist: jieba (==0.42.1)
Requires-Dist: redis (==4.6.0)
